patchshuffler/__init__.py
patchshuffler/base.py
patchshuffler/patch_shuffler.py
patchshuffler-0.1.1.dist-info/LICENSE
patchshuffler-0.1.1.dist-info/METADATA
patchshuffler-0.1.1.dist-info/WHEEL
patchshuffler-0.1.1.dist-info/top_level.txt
patchshuffler-0.1.1.dist-info/RECORD
