Metadata-Version: 2.1
Name: patchshuffler
Version: 0.1.1
Summary: A package for shuffling patches in time series patched data
Home-page: https://github.com/jaeho3690/patchshuffler
Author: Jaeho Kim
Author-email: jaeho3690@gmail.com
Classifier: Programming Language :: Python :: 3
Classifier: License :: OSI Approved :: MIT License
Classifier: Operating System :: OS Independent
Requires-Python: >=3.8
License-File: LICENSE
Requires-Dist: torch >=1.8.0
Requires-Dist: numpy >=1.20.0
Requires-Dist: pandas >=1.3.0
Requires-Dist: einops >=0.3.0
